src/__init__.py
src/temp.py
utils/__init__.py
utils/fileparse.py
test_packaging_name-0.0.1.dist-info/METADATA
test_packaging_name-0.0.1.dist-info/WHEEL
test_packaging_name-0.0.1.dist-info/top_level.txt
test_packaging_name-0.0.1.dist-info/RECORD
